README.md
setup.py
flask_resto/__init__.py
flask_resto/api.py
flask_resto/authorization.py
flask_resto/json.py
flask_resto/misc.py
flask_resto/params.py
flask_resto/resources.py
flask_resto.egg-info/PKG-INFO
flask_resto.egg-info/SOURCES.txt
flask_resto.egg-info/dependency_links.txt
flask_resto.egg-info/requires.txt
flask_resto.egg-info/top_level.txt